exceptions/__init__.py
exceptions/secret_exceptions.py
export_easy_package/__init__.py
export_easy_package/tools/__init__.py
export_easy_package/tools/export_esasy_gaia_determine_intent.py
export_easy_package/tools/export_esasy_gaia_determine_reply.py
export_easy_package/tools/my_tool_1.py
export_easy_package/tools/my_tool_2.py
export_easy_package/tools/tool_with_cascading_inputs.py
export_easy_package/tools/tool_with_custom_llm_type.py
export_easy_package/tools/tool_with_custom_strong_type_connection.py
export_easy_package/tools/tool_with_dynamic_list_input.py
export_easy_package/tools/tool_with_file_path_input.py
export_easy_package/tools/tool_with_generated_by_input.py
export_easy_package/tools/utils.py
my_tool_package/__init__.py
my_tool_package/tools/__init__.py
my_tool_package/tools/export_esasy_gaia_determine_intent.py
my_tool_package/tools/export_esasy_gaia_determine_reply.py
my_tool_package/tools/gaia_llm_custom.py
my_tool_package/tools/my_tool_1.py
my_tool_package/tools/my_tool_2.py
my_tool_package/tools/tool_with_cascading_inputs.py
my_tool_package/tools/tool_with_custom_llm_type.py
my_tool_package/tools/tool_with_custom_strong_type_connection.py
my_tool_package/tools/tool_with_dynamic_list_input.py
my_tool_package/tools/tool_with_file_path_input.py
my_tool_package/tools/tool_with_generated_by_input.py
my_tool_package/tools/utils.py
my_tool_package/yamls/export_esasy_gaia_determine_intent.yaml
my_tool_package/yamls/export_esasy_gaia_determine_reply.yaml
my_tool_package/yamls/gaia_llm_custom.yaml
my_tool_package/yamls/my_tool_1.yaml
my_tool_package/yamls/my_tool_2.yaml
my_tool_package/yamls/tool_with_cascading_inputs.yaml
my_tool_package/yamls/tool_with_custom_llm_type.yaml
my_tool_package/yamls/tool_with_custom_strong_type_connection.yaml
my_tool_package/yamls/tool_with_dynamic_list_input.yaml
my_tool_package/yamls/tool_with_file_path_input.yaml
my_tool_package/yamls/tool_with_generated_by_input.yaml
tests/__init__.py
tests/test_my_tool_1.py
export_easy_package-0.0.13.dist-info/METADATA
export_easy_package-0.0.13.dist-info/WHEEL
export_easy_package-0.0.13.dist-info/entry_points.txt
export_easy_package-0.0.13.dist-info/top_level.txt
export_easy_package-0.0.13.dist-info/RECORD
