Metadata-Version: 2.1
Name: export-easy-package
Version: 0.0.13
Summary: This is Export Easy Tools package
Provides-Extra: azure
Requires-Dist: azure-ai-ml<2.0.0,>=1.11.0; extra == "azure"
